algebraic_hbm/__init__.py
algebraic_hbm/algebraic_hbm.py
algebraic_hbm/fourier_series.py
algebraic_hbm/ode.py
algebraic_hbm/utils.py
algebraic_hbm-0.1.4.dist-info/LICENSE
algebraic_hbm-0.1.4.dist-info/METADATA
algebraic_hbm-0.1.4.dist-info/WHEEL
algebraic_hbm-0.1.4.dist-info/top_level.txt
algebraic_hbm-0.1.4.dist-info/RECORD
