Metadata-Version: 2.1
Name: algebraic_hbm
Version: 0.1.4
Summary: Python implementation of the algebraic harmonic balance method for second order ordinary differential equations with polynomial coefficients.
Home-page: https://git.tu-berlin.de/hannes.daenschel/algebraic-hbm
Author: Hannes Dänschel
Author-email: daenschel@math.tu-berlin.de
Classifier: Programming Language :: Python :: 3
Classifier: License :: OSI Approved :: MIT License
Classifier: Operating System :: OS Independent
Requires-Python: >=3.10
License-File: LICENSE
Requires-Dist: numba >=0.60.0
Requires-Dist: numpy >=1.26.4
Requires-Dist: scipy >=1.13.1
